plover_grandjean/__init__.py
plover_grandjean/system.py
plover_grandjean-0.0.1.dist-info/METADATA
plover_grandjean-0.0.1.dist-info/WHEEL
plover_grandjean-0.0.1.dist-info/entry_points.txt
plover_grandjean-0.0.1.dist-info/top_level.txt
plover_grandjean-0.0.1.dist-info/zip-safe
plover_grandjean-0.0.1.dist-info/RECORD
